.travis.yml
AUTHORS.md
CHANGELOG.md
LICENSE
MANIFEST.in
README.md
setup.cfg
setup.py
tox.ini
ci/bootstrap.py
src/.gitignore
src/momoapi/__init__.py
src/momoapi/__main__.py
src/momoapi/cli.py
src/momoapi/client.py
src/momoapi/collection.py
src/momoapi/config.py
src/momoapi/disbursement.py
src/momoapi/errors.py
src/momoapi/remittance.py
src/momoapi/utils.py
src/momoapi.egg-info/PKG-INFO
src/momoapi.egg-info/SOURCES.txt
src/momoapi.egg-info/dependency_links.txt
src/momoapi.egg-info/entry_points.txt
src/momoapi.egg-info/not-zip-safe
src/momoapi.egg-info/requires.txt
src/momoapi.egg-info/top_level.txt
tests/__init__.py
tests/integration/test_collection.py
tests/integration/test_disbursement.py
tests/integration/test_remittance.py
tests/integration/test_sandbox.py
tests/integration/features/collections.feature
tests/integration/features/disbursements.feature
tests/integration/features/remittances.feature
tests/integration/features/sandbox.feature
tests/unitests/__init__.py
tests/unitests/test_collection.py
tests/unitests/test_disbursement.py
tests/unitests/test_remittance.py
tests/unitests/utils.py