Metadata-Version: 2.1
Name: momoapi
Version: 1.0.1
Summary: Python wrapper for the MTN MoMo API.
Home-page: https://github.com/sparkplug/momoapi-python
Author: Sparkplug
Author-email: mugisha@sparkpl.ug
License: MIT license
Keywords: MoMo API,MoMo API Python Wrapper,MoMo API Python
Platform: UNKNOWN
Classifier: Development Status :: 5 - Production/Stable
Classifier: Intended Audience :: Developers
Classifier: License :: OSI Approved :: MIT License
Classifier: Operating System :: Unix
Classifier: Operating System :: POSIX
Classifier: Operating System :: Microsoft :: Windows
Classifier: Programming Language :: Python
Classifier: Programming Language :: Python :: 2.7
Classifier: Programming Language :: Python :: 3
Classifier: Programming Language :: Python :: 3.4
Classifier: Programming Language :: Python :: 3.5
Classifier: Programming Language :: Python :: 3.6
Classifier: Programming Language :: Python :: 3.7
Classifier: Programming Language :: Python :: Implementation :: CPython
Classifier: Programming Language :: Python :: Implementation :: PyPy
Classifier: Topic :: Utilities
Provides-Extra: test
Provides-Extra: dev
